{
  "protocol_version" : "0.0.6",
  "configuration" : {
    "version" : "(6.13.0) (explicit/664fdcba172)",
    "tlc" : "__thread",
    "sigsgev" : "normal",
    "notifications" : "kqueue",
    "architecture" : "arm64",
    "disabled_features" : "com,shared_perfcounters",
    "smallconfig" : "disabled",
    "bigarrays" : "disabled",
    "softdebug" : "enabled",
    "interpreter" : "enabled",
    "llvm_support" : "disabled",
    "suspend" : "preemptive"
  },
  "memory" : {
    "Resident Size" : "889864192",
    "Virtual Size" : "421898190848",
    "minor_gc_time" : "0",
    "major_gc_time" : "24529",
    "minor_gc_count" : "0",
    "major_gc_count" : "3",
    "major_gc_time_concurrent" : "0"
 },
  "threads" : [
 {
    "is_managed" : false,
    "offset_free_hash" : "0x0",
    "offset_rich_hash" : "0x0",
    "crashed" : false,
    "native_thread_id" : "0x172aa7000",
    "thread_info_addr" : "0x13e8ba200",
    "thread_name" : "Finalizer",
    "ctx" : {
      "IP" : "0x1c486a8ec",
      "SP" : "0x172aa6dd0",
      "BP" : "0x172aa6e50"
  },
    "unmanaged_frames" : [
  {
      "is_managed" : "false",
      "native_address" : "0x172d45c4c",
      "native_offset" : "0x00000"
   }
,
  {
      "is_managed" : "false",
      "native_address" : "0x172e7c788",
      "native_offset" : "0x00000"
   }
,
  {
      "is_managed" : "false",
      "native_address" : "0x172e7cae4",
      "native_offset" : "0x00000"
   }
,
  {
      "is_managed" : "false",
      "native_address" : "0x172e7c8ac",
      "native_offset" : "0x00000"
   }
,
  {
      "is_managed" : "false",
      "native_address" : "0x172d86bd4",
      "native_offset" : "0x00000"
   }
,
  {
      "is_managed" : "false",
      "native_address" : "0x1c48bf4a4",
      "native_offset" : "0x00000"
   }
,
  {
      "is_managed" : "false",
      "native_address" : "0x172eb6294",
      "native_offset" : "0x00000"
   }
,
  {
      "is_managed" : "false",
      "native_address" : "0x172e7d4f4",
      "native_offset" : "0x00000"
   }
,
  {
      "is_managed" : "false",
      "native_address" : "0x172e7d3a0",
      "native_offset" : "0x00000"
   }
,
  {
      "is_managed" : "false",
      "native_address" : "0x172efccb0",
      "native_offset" : "0x00000"
   }
,
  {
      "is_managed" : "false",
      "native_address" : "0x172efcc38",
      "native_offset" : "0x00000"
   }
,
  {
      "is_managed" : "false",
      "native_address" : "0x1c48a826c",
      "native_offset" : "0x00000"
   }
,
  {
      "is_managed" : "false",
      "native_address" : "0x1c48a308c",
      "native_offset" : "0x00000"
   }

  ]
 },
 {
    "is_managed" : false,
    "offset_free_hash" : "0x0",
    "offset_rich_hash" : "0x0",
    "crashed" : false,
    "native_thread_id" : "0x2da153000",
    "thread_info_addr" : "0x2b479c400",
    "thread_name" : "Thread Pool Worker",
    "ctx" : {
      "IP" : "0x1c486a904",
      "SP" : "0x2da152db0",
      "BP" : "0x2da152e50"
  },
    "unmanaged_frames" : [
  {
      "is_managed" : "false",
      "native_address" : "0x172d45c4c",
      "native_offset" : "0x00000"
   }
,
  {
      "is_managed" : "false",
      "native_address" : "0x172e7c788",
      "native_offset" : "0x00000"
   }
,
  {
      "is_managed" : "false",
      "native_address" : "0x172e7cae4",
      "native_offset" : "0x00000"
   }
,
  {
      "is_managed" : "false",
      "native_address" : "0x172e7c8ac",
      "native_offset" : "0x00000"
   }
,
  {
      "is_managed" : "false",
      "native_address" : "0x172d86bd4",
      "native_offset" : "0x00000"
   }
,
  {
      "is_managed" : "false",
      "native_address" : "0x1c48bf4a4",
      "native_offset" : "0x00000"
   }
,
  {
      "is_managed" : "false",
      "native_address" : "0x172dd4c70",
      "native_offset" : "0x00000"
   }
,
  {
      "is_managed" : "false",
      "native_address" : "0x172e7d4f4",
      "native_offset" : "0x00000"
   }
,
  {
      "is_managed" : "false",
      "native_address" : "0x172e7d3a0",
      "native_offset" : "0x00000"
   }
,
  {
      "is_managed" : "false",
      "native_address" : "0x172efccb0",
      "native_offset" : "0x00000"
   }
,
  {
      "is_managed" : "false",
      "native_address" : "0x172efcc38",
      "native_offset" : "0x00000"
   }
,
  {
      "is_managed" : "false",
      "native_address" : "0x1c48a826c",
      "native_offset" : "0x00000"
   }
,
  {
      "is_managed" : "false",
      "native_address" : "0x1c48a308c",
      "native_offset" : "0x00000"
   }

  ]
 },
 {
    "is_managed" : true,
    "offset_free_hash" : "0xfb24c93e6",
    "offset_rich_hash" : "0xfb24c956f",
    "crashed" : false,
    "native_thread_id" : "0x2ced47000",
    "thread_info_addr" : "0x13e0c0600",
    "thread_name" : "tid_1c803",
    "ctx" : {
      "IP" : "0x1c486e270",
      "SP" : "0x2ced46520",
      "BP" : "0x2ced465b0"
  },
    "managed_frames" : [
  {
      "is_managed" : "false",
      "native_address" : "unregistered"
   }
,
  {
      "is_managed" : "true",
      "guid" : "612A2C65-AAF8-43D6-98F8-D38B2AD7654A",
      "token" : "0x00000",
      "native_offset" : "0x0",
      "filename" : "mscorlib.dll",
      "sizeofimage" : "0x470000",
      "timestamp" : "0xd0713de6",
      "il_offset" : "0xffffffff"
   }
,
  {
      "is_managed" : "true",
      "guid" : "612A2C65-AAF8-43D6-98F8-D38B2AD7654A",
      "token" : "0x6001f5d",
      "native_offset" : "0x0",
      "filename" : "mscorlib.dll",
      "sizeofimage" : "0x470000",
      "timestamp" : "0xd0713de6",
      "il_offset" : "0x0002f"
   }
,
  {
      "is_managed" : "true",
      "guid" : "612A2C65-AAF8-43D6-98F8-D38B2AD7654A",
      "token" : "0x6001f50",
      "native_offset" : "0x0",
      "filename" : "mscorlib.dll",
      "sizeofimage" : "0x470000",
      "timestamp" : "0xd0713de6",
      "il_offset" : "0x0000e"
   }
,
  {
      "is_managed" : "true",
      "guid" : "612A2C65-AAF8-43D6-98F8-D38B2AD7654A",
      "token" : "0x6001f52",
      "native_offset" : "0x0",
      "filename" : "mscorlib.dll",
      "sizeofimage" : "0x470000",
      "timestamp" : "0xd0713de6",
      "il_offset" : "0x00000"
   }
,
  {
      "is_managed" : "true",
      "guid" : "EB829DFF-9616-411E-83EC-5826A0DB50FA",
      "token" : "0x6005a11",
      "native_offset" : "0x0",
      "filename" : "unityplastic.dll",
      "sizeofimage" : "0x4ec000",
      "timestamp" : "0x62c604f1",
      "il_offset" : "0x00030"
   }
,
  {
      "is_managed" : "true",
      "guid" : "612A2C65-AAF8-43D6-98F8-D38B2AD7654A",
      "token" : "0x6001f7d",
      "native_offset" : "0x0",
      "filename" : "mscorlib.dll",
      "sizeofimage" : "0x470000",
      "timestamp" : "0xd0713de6",
      "il_offset" : "0x00014"
   }
,
  {
      "is_managed" : "true",
      "guid" : "612A2C65-AAF8-43D6-98F8-D38B2AD7654A",
      "token" : "0x6001f25",
      "native_offset" : "0x0",
      "filename" : "mscorlib.dll",
      "sizeofimage" : "0x470000",
      "timestamp" : "0xd0713de6",
      "il_offset" : "0x00071"
   }
,
  {
      "is_managed" : "true",
      "guid" : "612A2C65-AAF8-43D6-98F8-D38B2AD7654A",
      "token" : "0x6001f23",
      "native_offset" : "0x0",
      "filename" : "mscorlib.dll",
      "sizeofimage" : "0x470000",
      "timestamp" : "0xd0713de6",
      "il_offset" : "0x00000"
   }
,
  {
      "is_managed" : "true",
      "guid" : "612A2C65-AAF8-43D6-98F8-D38B2AD7654A",
      "token" : "0x6001f22",
      "native_offset" : "0x0",
      "filename" : "mscorlib.dll",
      "sizeofimage" : "0x470000",
      "timestamp" : "0xd0713de6",
      "il_offset" : "0x0002b"
   }
,
  {
      "is_managed" : "true",
      "guid" : "612A2C65-AAF8-43D6-98F8-D38B2AD7654A",
      "token" : "0x6001f7f",
      "native_offset" : "0x0",
      "filename" : "mscorlib.dll",
      "sizeofimage" : "0x470000",
      "timestamp" : "0xd0713de6",
      "il_offset" : "0x00008"
   }
,
  {
      "is_managed" : "true",
      "guid" : "612A2C65-AAF8-43D6-98F8-D38B2AD7654A",
      "token" : "0x00000",
      "native_offset" : "0x0",
      "filename" : "mscorlib.dll",
      "sizeofimage" : "0x470000",
      "timestamp" : "0xd0713de6",
      "il_offset" : "0x00065"
   }

  ],
  "unmanaged_frames" : [
 {
    "is_managed" : "false",
    "native_address" : "0x172d45c4c",
    "native_offset" : "0x00000"
  }
,
 {
    "is_managed" : "false",
    "native_address" : "0x172e7c788",
    "native_offset" : "0x00000"
  }
,
 {
    "is_managed" : "false",
    "native_address" : "0x172e7cae4",
    "native_offset" : "0x00000"
  }
,
 {
    "is_managed" : "false",
    "native_address" : "0x172e7c8ac",
    "native_offset" : "0x00000"
  }
,
 {
    "is_managed" : "false",
    "native_address" : "0x172d86bd4",
    "native_offset" : "0x00000"
  }
,
 {
    "is_managed" : "false",
    "native_address" : "0x1c48bf4a4",
    "native_offset" : "0x00000"
  }
,
 {
    "is_managed" : "false",
    "native_address" : "0x1c48a8868",
    "native_offset" : "0x00000"
  }
,
 {
    "is_managed" : "false",
    "native_address" : "0x172ecbe08",
    "native_offset" : "0x00000"
  }
,
 {
    "is_managed" : "false",
    "native_address" : "0x172e884b0",
    "native_offset" : "0x00000"
  }
,
 {
    "is_managed" : "false",
    "native_address" : "0x172e882e4",
    "native_offset" : "0x00000"
  }
,
 {
    "is_managed" : "false",
    "native_address" : "0x172eb75d8",
    "native_offset" : "0x00000"
  }
,
 {
    "is_managed" : "false",
    "native_address" : "0x172e20c8c",
    "native_offset" : "0x00000"
  }
,
 {
    "is_managed" : "true",
    "guid" : "612A2C65-AAF8-43D6-98F8-D38B2AD7654A",
    "token" : "0x00000",
    "native_offset" : "0x0",
    "filename" : "mscorlib.dll",
    "sizeofimage" : "0x470000",
    "timestamp" : "0xd0713de6",
    "il_offset" : "0x00000"
  }
,
 {
    "is_managed" : "true",
    "guid" : "612A2C65-AAF8-43D6-98F8-D38B2AD7654A",
    "token" : "0x6001f5d",
    "native_offset" : "0x0",
    "filename" : "mscorlib.dll",
    "sizeofimage" : "0x470000",
    "timestamp" : "0xd0713de6",
    "il_offset" : "0x00000"
  }
,
 {
    "is_managed" : "true",
    "guid" : "612A2C65-AAF8-43D6-98F8-D38B2AD7654A",
    "token" : "0x6001f50",
    "native_offset" : "0x0",
    "filename" : "mscorlib.dll",
    "sizeofimage" : "0x470000",
    "timestamp" : "0xd0713de6",
    "il_offset" : "0x00000"
  }
,
 {
    "is_managed" : "true",
    "guid" : "612A2C65-AAF8-43D6-98F8-D38B2AD7654A",
    "token" : "0x6001f52",
    "native_offset" : "0x0",
    "filename" : "mscorlib.dll",
    "sizeofimage" : "0x470000",
    "timestamp" : "0xd0713de6",
    "il_offset" : "0x00000"
  }
,
 {
    "is_managed" : "true",
    "guid" : "EB829DFF-9616-411E-83EC-5826A0DB50FA",
    "token" : "0x6005a11",
    "native_offset" : "0x0",
    "filename" : "unityplastic.dll",
    "sizeofimage" : "0x4ec000",
    "timestamp" : "0x62c604f1",
    "il_offset" : "0x00000"
  }
,
 {
    "is_managed" : "true",
    "guid" : "612A2C65-AAF8-43D6-98F8-D38B2AD7654A",
    "token" : "0x6001f7d",
    "native_offset" : "0x0",
    "filename" : "mscorlib.dll",
    "sizeofimage" : "0x470000",
    "timestamp" : "0xd0713de6",
    "il_offset" : "0x00000"
  }
,
 {
    "is_managed" : "true",
    "guid" : "612A2C65-AAF8-43D6-98F8-D38B2AD7654A",
    "token" : "0x6001f25",
    "native_offset" : "0x0",
    "filename" : "mscorlib.dll",
    "sizeofimage" : "0x470000",
    "timestamp" : "0xd0713de6",
    "il_offset" : "0x00000"
  }
,
 {
    "is_managed" : "true",
    "guid" : "612A2C65-AAF8-43D6-98F8-D38B2AD7654A",
    "token" : "0x6001f23",
    "native_offset" : "0x0",
    "filename" : "mscorlib.dll",
    "sizeofimage" : "0x470000",
    "timestamp" : "0xd0713de6",
    "il_offset" : "0x00000"
  }
,
 {
    "is_managed" : "true",
    "guid" : "612A2C65-AAF8-43D6-98F8-D38B2AD7654A",
    "token" : "0x6001f22",
    "native_offset" : "0x0",
    "filename" : "mscorlib.dll",
    "sizeofimage" : "0x470000",
    "timestamp" : "0xd0713de6",
    "il_offset" : "0x00000"
  }
,
 {
    "is_managed" : "true",
    "guid" : "612A2C65-AAF8-43D6-98F8-D38B2AD7654A",
    "token" : "0x6001f7f",
    "native_offset" : "0x0",
    "filename" : "mscorlib.dll",
    "sizeofimage" : "0x470000",
    "timestamp" : "0xd0713de6",
    "il_offset" : "0x00000"
  }
,
 {
    "is_managed" : "true",
    "guid" : "612A2C65-AAF8-43D6-98F8-D38B2AD7654A",
    "token" : "0x00000",
    "native_offset" : "0x0",
    "filename" : "mscorlib.dll",
    "sizeofimage" : "0x470000",
    "timestamp" : "0xd0713de6",
    "il_offset" : "0x00000"
  }
,
 {
    "is_managed" : "false",
    "native_address" : "0x172cd58e0",
    "native_offset" : "0x00000"
  }
,
 {
    "is_managed" : "false",
    "native_address" : "0x172e5b6a8",
    "native_offset" : "0x00000"
  }
,
 {
    "is_managed" : "false",
    "native_address" : "0x172e5d2a4",
    "native_offset" : "0x00000"
  }
,
 {
    "is_managed" : "false",
    "native_address" : "0x172e7d5e8",
    "native_offset" : "0x00000"
  }
,
 {
    "is_managed" : "false",
    "native_address" : "0x172e7d3a0",
    "native_offset" : "0x00000"
  }
,
 {
    "is_managed" : "false",
    "native_address" : "0x172efccb0",
    "native_offset" : "0x00000"
  }
,
 {
    "is_managed" : "false",
    "native_address" : "0x172efcc38",
    "native_offset" : "0x00000"
  }
,
 {
    "is_managed" : "false",
    "native_address" : "0x1c48a826c",
    "native_offset" : "0x00000"
  }
,
 {
    "is_managed" : "false",
    "native_address" : "0x1c48a308c",
    "native_offset" : "0x00000"
  }

 ]
},
{
  "is_managed" : false,
  "offset_free_hash" : "0x0",
  "offset_rich_hash" : "0x0",
  "crashed" : false,
  "native_thread_id" : "0x2b71c7000",
  "thread_info_addr" : "0x2b33fd000",
  "thread_name" : "tid_24603",
  "ctx" : {
    "IP" : "0x1c486a8ec",
    "SP" : "0x2b71c6d80",
    "BP" : "0x2b71c6d90"
 },
  "unmanaged_frames" : [
 {
    "is_managed" : "false",
    "native_address" : "0x172d45c4c",
    "native_offset" : "0x00000"
  }
,
 {
    "is_managed" : "false",
    "native_address" : "0x172e7c788",
    "native_offset" : "0x00000"
  }
,
 {
    "is_managed" : "false",
    "native_address" : "0x172e7cae4",
    "native_offset" : "0x00000"
  }
,
 {
    "is_managed" : "false",
    "native_address" : "0x172e7c8ac",
    "native_offset" : "0x00000"
  }
,
 {
    "is_managed" : "false",
    "native_address" : "0x172d86bd4",
    "native_offset" : "0x00000"
  }
,
 {
    "is_managed" : "false",
    "native_address" : "0x1c48bf4a4",
    "native_offset" : "0x00000"
  }
,
 {
    "is_managed" : "false",
    "native_address" : "0x1c46e4750",
    "native_offset" : "0x00000"
  }
,
 {
    "is_managed" : "false",
    "native_address" : "0x1c46e4df8",
    "native_offset" : "0x00000"
  }
,
 {
    "is_managed" : "false",
    "native_address" : "0x102ce192c",
    "native_offset" : "0x00000"
  }
,
 {
    "is_managed" : "false",
    "native_address" : "0x100817d70",
    "native_offset" : "0x00000"
  }
,
 {
    "is_managed" : "false",
    "native_address" : "0x100bc448c",
    "native_offset" : "0x00000"
  }
,
 {
    "is_managed" : "false",
    "native_address" : "0x100bc4428",
    "native_offset" : "0x00000"
  }
,
 {
    "is_managed" : "false",
    "native_address" : "0x100d4c4d8",
    "native_offset" : "0x00000"
  }
,
 {
    "is_managed" : "false",
    "native_address" : "0x1c48a826c",
    "native_offset" : "0x00000"
  }
,
 {
    "is_managed" : "false",
    "native_address" : "0x1c48a308c",
    "native_offset" : "0x00000"
  }

 ]
},
{
  "is_managed" : false,
  "offset_free_hash" : "0x0",
  "offset_rich_hash" : "0x0",
  "crashed" : false,
  "native_thread_id" : "0x2da8eb000",
  "thread_info_addr" : "0x11f83d600",
  "thread_name" : "Thread Pool Worker",
  "ctx" : {
    "IP" : "0x1c486a904",
    "SP" : "0x2da8eadb0",
    "BP" : "0x2da8eae50"
 },
  "unmanaged_frames" : [
 {
    "is_managed" : "false",
    "native_address" : "0x172d45c4c",
    "native_offset" : "0x00000"
  }
,
 {
    "is_managed" : "false",
    "native_address" : "0x172e7c788",
    "native_offset" : "0x00000"
  }
,
 {
    "is_managed" : "false",
    "native_address" : "0x172e7cae4",
    "native_offset" : "0x00000"
  }
,
 {
    "is_managed" : "false",
    "native_address" : "0x172e7c8ac",
    "native_offset" : "0x00000"
  }
,
 {
    "is_managed" : "false",
    "native_address" : "0x172d86bd4",
    "native_offset" : "0x00000"
  }
,
 {
    "is_managed" : "false",
    "native_address" : "0x1c48bf4a4",
    "native_offset" : "0x00000"
  }
,
 {
    "is_managed" : "false",
    "native_address" : "0x172dd4c70",
    "native_offset" : "0x00000"
  }
,
 {
    "is_managed" : "false",
    "native_address" : "0x172e7d4f4",
    "native_offset" : "0x00000"
  }
,
 {
    "is_managed" : "false",
    "native_address" : "0x172e7d3a0",
    "native_offset" : "0x00000"
  }
,
 {
    "is_managed" : "false",
    "native_address" : "0x172efccb0",
    "native_offset" : "0x00000"
  }
,
 {
    "is_managed" : "false",
    "native_address" : "0x172efcc38",
    "native_offset" : "0x00000"
  }
,
 {
    "is_managed" : "false",
    "native_address" : "0x1c48a826c",
    "native_offset" : "0x00000"
  }
,
 {
    "is_managed" : "false",
    "native_address" : "0x1c48a308c",
    "native_offset" : "0x00000"
  }

 ]
},
{
  "is_managed" : false,
  "offset_free_hash" : "0x0",
  "offset_rich_hash" : "0x0",
  "crashed" : false,
  "native_thread_id" : "0x172cb3000",
  "thread_info_addr" : "0x13e8bd400",
  "thread_name" : "Debugger agent",
  "ctx" : {
    "IP" : "0x1c4872e84",
    "SP" : "0x172cb2aa0",
    "BP" : "0x172cb2ae0"
 },
  "unmanaged_frames" : [
 {
    "is_managed" : "false",
    "native_address" : "0x172d45c4c",
    "native_offset" : "0x00000"
  }
,
 {
    "is_managed" : "false",
    "native_address" : "0x172e7c788",
    "native_offset" : "0x00000"
  }
,
 {
    "is_managed" : "false",
    "native_address" : "0x172e7cae4",
    "native_offset" : "0x00000"
  }
,
 {
    "is_managed" : "false",
    "native_address" : "0x172e7c8ac",
    "native_offset" : "0x00000"
  }
,
 {
    "is_managed" : "false",
    "native_address" : "0x172d86bd4",
    "native_offset" : "0x00000"
  }
,
 {
    "is_managed" : "false",
    "native_address" : "0x1c48bf4a4",
    "native_offset" : "0x00000"
  }
,
 {
    "is_managed" : "false",
    "native_address" : "0x172dbc3e0",
    "native_offset" : "0x00000"
  }
,
 {
    "is_managed" : "false",
    "native_address" : "0x172db3760",
    "native_offset" : "0x00000"
  }
,
 {
    "is_managed" : "false",
    "native_address" : "0x172e7d4f4",
    "native_offset" : "0x00000"
  }
,
 {
    "is_managed" : "false",
    "native_address" : "0x172e7d3a0",
    "native_offset" : "0x00000"
  }
,
 {
    "is_managed" : "false",
    "native_address" : "0x172efccb0",
    "native_offset" : "0x00000"
  }
,
 {
    "is_managed" : "false",
    "native_address" : "0x172efcc38",
    "native_offset" : "0x00000"
  }
,
 {
    "is_managed" : "false",
    "native_address" : "0x1c48a826c",
    "native_offset" : "0x00000"
  }
,
 {
    "is_managed" : "false",
    "native_address" : "0x1c48a308c",
    "native_offset" : "0x00000"
  }

 ]
},
{
  "is_managed" : false,
  "offset_free_hash" : "0x0",
  "offset_rich_hash" : "0x0",
  "crashed" : false,
  "native_thread_id" : "0x2dc68f000",
  "thread_info_addr" : "0x13e736800",
  "thread_name" : "Thread Pool Worker",
  "ctx" : {
    "IP" : "0x1c486a904",
    "SP" : "0x2dc68edb0",
    "BP" : "0x2dc68ee50"
 },
  "unmanaged_frames" : [
 {
    "is_managed" : "false",
    "native_address" : "0x172d45c4c",
    "native_offset" : "0x00000"
  }
,
 {
    "is_managed" : "false",
    "native_address" : "0x172e7c788",
    "native_offset" : "0x00000"
  }
,
 {
    "is_managed" : "false",
    "native_address" : "0x172e7cae4",
    "native_offset" : "0x00000"
  }
,
 {
    "is_managed" : "false",
    "native_address" : "0x172e7c8ac",
    "native_offset" : "0x00000"
  }
,
 {
    "is_managed" : "false",
    "native_address" : "0x172d86bd4",
    "native_offset" : "0x00000"
  }
,
 {
    "is_managed" : "false",
    "native_address" : "0x1c48bf4a4",
    "native_offset" : "0x00000"
  }
,
 {
    "is_managed" : "false",
    "native_address" : "0x172dd4c70",
    "native_offset" : "0x00000"
  }
,
 {
    "is_managed" : "false",
    "native_address" : "0x172e7d4f4",
    "native_offset" : "0x00000"
  }
,
 {
    "is_managed" : "false",
    "native_address" : "0x172e7d3a0",
    "native_offset" : "0x00000"
  }
,
 {
    "is_managed" : "false",
    "native_address" : "0x172efccb0",
    "native_offset" : "0x00000"
  }
,
 {
    "is_managed" : "false",
    "native_address" : "0x172efcc38",
    "native_offset" : "0x00000"
  }
,
 {
    "is_managed" : "false",
    "native_address" : "0x1c48a826c",
    "native_offset" : "0x00000"
  }
,
 {
    "is_managed" : "false",
    "native_address" : "0x1c48a308c",
    "native_offset" : "0x00000"
  }

 ]
},
{
  "is_managed" : true,
  "offset_free_hash" : "0x1224727402",
  "offset_rich_hash" : "0x12247275cb",
  "crashed" : false,
  "native_thread_id" : "0x2b4a07000",
  "thread_info_addr" : "0x13f084600",
  "thread_name" : "Timer-Scheduler",
  "ctx" : {
    "IP" : "0x1c486e270",
    "SP" : "0x2b4a05ec0",
    "BP" : "0x2b4a05f50"
 },
  "managed_frames" : [
 {
    "is_managed" : "false",
    "native_address" : "unregistered"
  }
,
 {
    "is_managed" : "true",
    "guid" : "612A2C65-AAF8-43D6-98F8-D38B2AD7654A",
    "token" : "0x00000",
    "native_offset" : "0x0",
    "filename" : "mscorlib.dll",
    "sizeofimage" : "0x470000",
    "timestamp" : "0xd0713de6",
    "il_offset" : "0xffffffff"
  }
,
 {
    "is_managed" : "true",
    "guid" : "612A2C65-AAF8-43D6-98F8-D38B2AD7654A",
    "token" : "0x60020b2",
    "native_offset" : "0x0",
    "filename" : "mscorlib.dll",
    "sizeofimage" : "0x470000",
    "timestamp" : "0xd0713de6",
    "il_offset" : "0x00044"
  }
,
 {
    "is_managed" : "true",
    "guid" : "612A2C65-AAF8-43D6-98F8-D38B2AD7654A",
    "token" : "0x600209e",
    "native_offset" : "0x0",
    "filename" : "mscorlib.dll",
    "sizeofimage" : "0x470000",
    "timestamp" : "0xd0713de6",
    "il_offset" : "0x00014"
  }
,
 {
    "is_managed" : "true",
    "guid" : "612A2C65-AAF8-43D6-98F8-D38B2AD7654A",
    "token" : "0x600209d",
    "native_offset" : "0x0",
    "filename" : "mscorlib.dll",
    "sizeofimage" : "0x470000",
    "timestamp" : "0xd0713de6",
    "il_offset" : "0x00000"
  }
,
 {
    "is_managed" : "true",
    "guid" : "612A2C65-AAF8-43D6-98F8-D38B2AD7654A",
    "token" : "0x6002098",
    "native_offset" : "0x0",
    "filename" : "mscorlib.dll",
    "sizeofimage" : "0x470000",
    "timestamp" : "0xd0713de6",
    "il_offset" : "0x00019"
  }
,
 {
    "is_managed" : "true",
    "guid" : "612A2C65-AAF8-43D6-98F8-D38B2AD7654A",
    "token" : "0x600209b",
    "native_offset" : "0x0",
    "filename" : "mscorlib.dll",
    "sizeofimage" : "0x470000",
    "timestamp" : "0xd0713de6",
    "il_offset" : "0x00000"
  }
,
 {
    "is_managed" : "true",
    "guid" : "612A2C65-AAF8-43D6-98F8-D38B2AD7654A",
    "token" : "0x600215a",
    "native_offset" : "0x0",
    "filename" : "mscorlib.dll",
    "sizeofimage" : "0x470000",
    "timestamp" : "0xd0713de6",
    "il_offset" : "0x0003c"
  }
,
 {
    "is_managed" : "true",
    "guid" : "612A2C65-AAF8-43D6-98F8-D38B2AD7654A",
    "token" : "0x6001f7d",
    "native_offset" : "0x0",
    "filename" : "mscorlib.dll",
    "sizeofimage" : "0x470000",
    "timestamp" : "0xd0713de6",
    "il_offset" : "0x00014"
  }
,
 {
    "is_managed" : "true",
    "guid" : "612A2C65-AAF8-43D6-98F8-D38B2AD7654A",
    "token" : "0x6001f25",
    "native_offset" : "0x0",
    "filename" : "mscorlib.dll",
    "sizeofimage" : "0x470000",
    "timestamp" : "0xd0713de6",
    "il_offset" : "0x00071"
  }
,
 {
    "is_managed" : "true",
    "guid" : "612A2C65-AAF8-43D6-98F8-D38B2AD7654A",
    "token" : "0x6001f23",
    "native_offset" : "0x0",
    "filename" : "mscorlib.dll",
    "sizeofimage" : "0x470000",
    "timestamp" : "0xd0713de6",
    "il_offset" : "0x00000"
  }
,
 {
    "is_managed" : "true",
    "guid" : "612A2C65-AAF8-43D6-98F8-D38B2AD7654A",
    "token" : "0x6001f22",
    "native_offset" : "0x0",
    "filename" : "mscorlib.dll",
    "sizeofimage" : "0x470000",
    "timestamp" : "0xd0713de6",
    "il_offset" : "0x0002b"
  }
,
 {
    "is_managed" : "true",
    "guid" : "612A2C65-AAF8-43D6-98F8-D38B2AD7654A",
    "token" : "0x6001f7f",
    "native_offset" : "0x0",
    "filename" : "mscorlib.dll",
    "sizeofimage" : "0x470000",
    "timestamp" : "0xd0713de6",
    "il_offset" : "0x00008"
  }
,
 {
    "is_managed" : "true",
    "guid" : "612A2C65-AAF8-43D6-98F8-D38B2AD7654A",
    "token" : "0x00000",
    "native_offset" : "0x0",
    "filename" : "mscorlib.dll",
    "sizeofimage" : "0x470000",
    "timestamp" : "0xd0713de6",
    "il_offset" : "0x00065"
  }

 ],
"unmanaged_frames" : [
{
  "is_managed" : "false",
  "native_address" : "0x172d45c4c",
  "native_offset" : "0x00000"
 }
,
{
  "is_managed" : "false",
  "native_address" : "0x172e7c788",
  "native_offset" : "0x00000"
 }
,
{
  "is_managed" : "false",
  "native_address" : "0x172e7cae4",
  "native_offset" : "0x00000"
 }
,
{
  "is_managed" : "false",
  "native_address" : "0x172e7c8ac",
  "native_offset" : "0x00000"
 }
,
{
  "is_managed" : "false",
  "native_address" : "0x172d86bd4",
  "native_offset" : "0x00000"
 }
,
{
  "is_managed" : "false",
  "native_address" : "0x1c48bf4a4",
  "native_offset" : "0x00000"
 }
,
{
  "is_managed" : "false",
  "native_address" : "0x1c48a883c",
  "native_offset" : "0x00000"
 }
,
{
  "is_managed" : "false",
  "native_address" : "0x172ecbe30",
  "native_offset" : "0x00000"
 }
,
{
  "is_managed" : "false",
  "native_address" : "0x172e884b0",
  "native_offset" : "0x00000"
 }
,
{
  "is_managed" : "false",
  "native_address" : "0x172e882e4",
  "native_offset" : "0x00000"
 }
,
{
  "is_managed" : "false",
  "native_address" : "0x172e8857c",
  "native_offset" : "0x00000"
 }
,
{
  "is_managed" : "false",
  "native_address" : "0x172e77b28",
  "native_offset" : "0x00000"
 }
,
{
  "is_managed" : "false",
  "native_address" : "0x172e22388",
  "native_offset" : "0x00000"
 }
,
{
  "is_managed" : "true",
  "guid" : "612A2C65-AAF8-43D6-98F8-D38B2AD7654A",
  "token" : "0x00000",
  "native_offset" : "0x0",
  "filename" : "mscorlib.dll",
  "sizeofimage" : "0x470000",
  "timestamp" : "0xd0713de6",
  "il_offset" : "0x00000"
 }
,
{
  "is_managed" : "true",
  "guid" : "612A2C65-AAF8-43D6-98F8-D38B2AD7654A",
  "token" : "0x60020b2",
  "native_offset" : "0x0",
  "filename" : "mscorlib.dll",
  "sizeofimage" : "0x470000",
  "timestamp" : "0xd0713de6",
  "il_offset" : "0x00000"
 }
,
{
  "is_managed" : "true",
  "guid" : "612A2C65-AAF8-43D6-98F8-D38B2AD7654A",
  "token" : "0x600209e",
  "native_offset" : "0x0",
  "filename" : "mscorlib.dll",
  "sizeofimage" : "0x470000",
  "timestamp" : "0xd0713de6",
  "il_offset" : "0x00000"
 }
,
{
  "is_managed" : "true",
  "guid" : "612A2C65-AAF8-43D6-98F8-D38B2AD7654A",
  "token" : "0x600209d",
  "native_offset" : "0x0",
  "filename" : "mscorlib.dll",
  "sizeofimage" : "0x470000",
  "timestamp" : "0xd0713de6",
  "il_offset" : "0x00000"
 }
,
{
  "is_managed" : "true",
  "guid" : "612A2C65-AAF8-43D6-98F8-D38B2AD7654A",
  "token" : "0x6002098",
  "native_offset" : "0x0",
  "filename" : "mscorlib.dll",
  "sizeofimage" : "0x470000",
  "timestamp" : "0xd0713de6",
  "il_offset" : "0x00000"
 }
,
{
  "is_managed" : "true",
  "guid" : "612A2C65-AAF8-43D6-98F8-D38B2AD7654A",
  "token" : "0x600209b",
  "native_offset" : "0x0",
  "filename" : "mscorlib.dll",
  "sizeofimage" : "0x470000",
  "timestamp" : "0xd0713de6",
  "il_offset" : "0x00000"
 }
,
{
  "is_managed" : "true",
  "guid" : "612A2C65-AAF8-43D6-98F8-D38B2AD7654A",
  "token" : "0x600215a",
  "native_offset" : "0x0",
  "filename" : "mscorlib.dll",
  "sizeofimage" : "0x470000",
  "timestamp" : "0xd0713de6",
  "il_offset" : "0x00000"
 }
,
{
  "is_managed" : "true",
  "guid" : "612A2C65-AAF8-43D6-98F8-D38B2AD7654A",
  "token" : "0x6001f7d",
  "native_offset" : "0x0",
  "filename" : "mscorlib.dll",
  "sizeofimage" : "0x470000",
  "timestamp" : "0xd0713de6",
  "il_offset" : "0x00000"
 }
,
{
  "is_managed" : "true",
  "guid" : "612A2C65-AAF8-43D6-98F8-D38B2AD7654A",
  "token" : "0x6001f25",
  "native_offset" : "0x0",
  "filename" : "mscorlib.dll",
  "sizeofimage" : "0x470000",
  "timestamp" : "0xd0713de6",
  "il_offset" : "0x00000"
 }
,
{
  "is_managed" : "true",
  "guid" : "612A2C65-AAF8-43D6-98F8-D38B2AD7654A",
  "token" : "0x6001f23",
  "native_offset" : "0x0",
  "filename" : "mscorlib.dll",
  "sizeofimage" : "0x470000",
  "timestamp" : "0xd0713de6",
  "il_offset" : "0x00000"
 }
,
{
  "is_managed" : "true",
  "guid" : "612A2C65-AAF8-43D6-98F8-D38B2AD7654A",
  "token" : "0x6001f22",
  "native_offset" : "0x0",
  "filename" : "mscorlib.dll",
  "sizeofimage" : "0x470000",
  "timestamp" : "0xd0713de6",
  "il_offset" : "0x00000"
 }
,
{
  "is_managed" : "true",
  "guid" : "612A2C65-AAF8-43D6-98F8-D38B2AD7654A",
  "token" : "0x6001f7f",
  "native_offset" : "0x0",
  "filename" : "mscorlib.dll",
  "sizeofimage" : "0x470000",
  "timestamp" : "0xd0713de6",
  "il_offset" : "0x00000"
 }
,
{
  "is_managed" : "true",
  "guid" : "612A2C65-AAF8-43D6-98F8-D38B2AD7654A",
  "token" : "0x00000",
  "native_offset" : "0x0",
  "filename" : "mscorlib.dll",
  "sizeofimage" : "0x470000",
  "timestamp" : "0xd0713de6",
  "il_offset" : "0x00000"
 }
,
{
  "is_managed" : "false",
  "native_address" : "0x172cd58e0",
  "native_offset" : "0x00000"
 }
,
{
  "is_managed" : "false",
  "native_address" : "0x172e5b6a8",
  "native_offset" : "0x00000"
 }
,
{
  "is_managed" : "false",
  "native_address" : "0x172e5d2a4",
  "native_offset" : "0x00000"
 }
,
{
  "is_managed" : "false",
  "native_address" : "0x172e7d5e8",
  "native_offset" : "0x00000"
 }
,
{
  "is_managed" : "false",
  "native_address" : "0x172e7d3a0",
  "native_offset" : "0x00000"
 }
,
{
  "is_managed" : "false",
  "native_address" : "0x172efccb0",
  "native_offset" : "0x00000"
 }
,
{
  "is_managed" : "false",
  "native_address" : "0x172efcc38",
  "native_offset" : "0x00000"
 }
,
{
  "is_managed" : "false",
  "native_address" : "0x1c48a826c",
  "native_offset" : "0x00000"
 }
,
{
  "is_managed" : "false",
  "native_address" : "0x1c48a308c",
  "native_offset" : "0x00000"
 }

]
},
{
"is_managed" : false,
"offset_free_hash" : "0x0",
"offset_rich_hash" : "0x0",
"crashed" : false,
"native_thread_id" : "0x2d9a07000",
"thread_info_addr" : "0x2b46ec000",
"thread_name" : "Thread Pool Worker",
"ctx" : {
  "IP" : "0x1c486a904",
  "SP" : "0x2d9a06db0",
  "BP" : "0x2d9a06e50"
},
"unmanaged_frames" : [
{
  "is_managed" : "false",
  "native_address" : "0x172d45c4c",
  "native_offset" : "0x00000"
 }
,
{
  "is_managed" : "false",
  "native_address" : "0x172e7c788",
  "native_offset" : "0x00000"
 }
,
{
  "is_managed" : "false",
  "native_address" : "0x172e7cae4",
  "native_offset" : "0x00000"
 }
,
{
  "is_managed" : "false",
  "native_address" : "0x172e7c8ac",
  "native_offset" : "0x00000"
 }
,
{
  "is_managed" : "false",
  "native_address" : "0x172d86bd4",
  "native_offset" : "0x00000"
 }
,
{
  "is_managed" : "false",
  "native_address" : "0x1c48bf4a4",
  "native_offset" : "0x00000"
 }
,
{
  "is_managed" : "false",
  "native_address" : "0x172dd4c70",
  "native_offset" : "0x00000"
 }
,
{
  "is_managed" : "false",
  "native_address" : "0x172e7d4f4",
  "native_offset" : "0x00000"
 }
,
{
  "is_managed" : "false",
  "native_address" : "0x172e7d3a0",
  "native_offset" : "0x00000"
 }
,
{
  "is_managed" : "false",
  "native_address" : "0x172efccb0",
  "native_offset" : "0x00000"
 }
,
{
  "is_managed" : "false",
  "native_address" : "0x172efcc38",
  "native_offset" : "0x00000"
 }
,
{
  "is_managed" : "false",
  "native_address" : "0x1c48a826c",
  "native_offset" : "0x00000"
 }
,
{
  "is_managed" : "false",
  "native_address" : "0x1c48a308c",
  "native_offset" : "0x00000"
 }

]
},
{
"is_managed" : false,
"offset_free_hash" : "0x0",
"offset_rich_hash" : "0x0",
"crashed" : false,
"native_thread_id" : "0x2dab83000",
"thread_info_addr" : "0x2ca0e7e00",
"thread_name" : "tid_24f13",
"ctx" : {
  "IP" : "0x1c486e270",
  "SP" : "0x2dab82c20",
  "BP" : "0x2dab82cb0"
},
"unmanaged_frames" : [
{
  "is_managed" : "false",
  "native_address" : "0x172d45c4c",
  "native_offset" : "0x00000"
 }
,
{
  "is_managed" : "false",
  "native_address" : "0x172e7c788",
  "native_offset" : "0x00000"
 }
,
{
  "is_managed" : "false",
  "native_address" : "0x172e7cae4",
  "native_offset" : "0x00000"
 }
,
{
  "is_managed" : "false",
  "native_address" : "0x172e7c8ac",
  "native_offset" : "0x00000"
 }
,
{
  "is_managed" : "false",
  "native_address" : "0x172d86bd4",
  "native_offset" : "0x00000"
 }
,
{
  "is_managed" : "false",
  "native_address" : "0x1c48bf4a4",
  "native_offset" : "0x00000"
 }
,
{
  "is_managed" : "false",
  "native_address" : "0x1c48a8868",
  "native_offset" : "0x00000"
 }
,
{
  "is_managed" : "false",
  "native_address" : "0x172ecbe08",
  "native_offset" : "0x00000"
 }
,
{
  "is_managed" : "false",
  "native_address" : "0x172ed5ae4",
  "native_offset" : "0x00000"
 }
,
{
  "is_managed" : "false",
  "native_address" : "0x172dd4478",
  "native_offset" : "0x00000"
 }
,
{
  "is_managed" : "false",
  "native_address" : "0x172e7d4f4",
  "native_offset" : "0x00000"
 }
,
{
  "is_managed" : "false",
  "native_address" : "0x172e7d3a0",
  "native_offset" : "0x00000"
 }
,
{
  "is_managed" : "false",
  "native_address" : "0x172efccb0",
  "native_offset" : "0x00000"
 }
,
{
  "is_managed" : "false",
  "native_address" : "0x172efcc38",
  "native_offset" : "0x00000"
 }
,
{
  "is_managed" : "false",
  "native_address" : "0x1c48a826c",
  "native_offset" : "0x00000"
 }
,
{
  "is_managed" : "false",
  "native_address" : "0x1c48a308c",
  "native_offset" : "0x00000"
 }

]
},
{
"is_managed" : true,
"offset_free_hash" : "0xa569772a0",
"offset_rich_hash" : "0xa5697763a",
"crashed" : true,
"native_thread_id" : "0x106010580",
"thread_info_addr" : "0x13d08de00",
"thread_name" : "tid_103",
"ctx" : {
  "IP" : "0x100cdec28",
  "SP" : "0x16fb51f30",
  "BP" : "0x16fb51f40"
},
"managed_frames" : [
{
  "is_managed" : "false",
  "native_address" : "unregistered"
 }
,
{
  "is_managed" : "true",
  "guid" : "10F522B7-3746-4037-B248-E9A3C3BD7C67",
  "token" : "0x00000",
  "native_offset" : "0x0",
  "filename" : "UnityEditor.CoreModule.dll",
  "sizeofimage" : "0x81a000",
  "timestamp" : "0x97e985a9",
  "il_offset" : "0xffffffff"
 }
,
{
  "is_managed" : "true",
  "guid" : "10F522B7-3746-4037-B248-E9A3C3BD7C67",
  "token" : "0x6007ed4",
  "native_offset" : "0x0",
  "filename" : "UnityEditor.CoreModule.dll",
  "sizeofimage" : "0x81a000",
  "timestamp" : "0x97e985a9",
  "il_offset" : "0x00001"
 }
,
{
  "is_managed" : "true",
  "guid" : "10F522B7-3746-4037-B248-E9A3C3BD7C67",
  "token" : "0x6007f3b",
  "native_offset" : "0x0",
  "filename" : "UnityEditor.CoreModule.dll",
  "sizeofimage" : "0x81a000",
  "timestamp" : "0x97e985a9",
  "il_offset" : "0x00317"
 }
,
{
  "is_managed" : "true",
  "guid" : "10F522B7-3746-4037-B248-E9A3C3BD7C67",
  "token" : "0x6007dcf",
  "native_offset" : "0x0",
  "filename" : "UnityEditor.CoreModule.dll",
  "sizeofimage" : "0x81a000",
  "timestamp" : "0x97e985a9",
  "il_offset" : "0x0000e"
 }
,
{
  "is_managed" : "true",
  "guid" : "10F522B7-3746-4037-B248-E9A3C3BD7C67",
  "token" : "0x6007db9",
  "native_offset" : "0x0",
  "filename" : "UnityEditor.CoreModule.dll",
  "sizeofimage" : "0x81a000",
  "timestamp" : "0x97e985a9",
  "il_offset" : "0x00041"
 }
,
{
  "is_managed" : "true",
  "guid" : "10F522B7-3746-4037-B248-E9A3C3BD7C67",
  "token" : "0x6001f4a",
  "native_offset" : "0x0",
  "filename" : "UnityEditor.CoreModule.dll",
  "sizeofimage" : "0x81a000",
  "timestamp" : "0x97e985a9",
  "il_offset" : "0x0000a"
 }
,
{
  "is_managed" : "true",
  "guid" : "612A2C65-AAF8-43D6-98F8-D38B2AD7654A",
  "token" : "0x00000",
  "native_offset" : "0x0",
  "filename" : "mscorlib.dll",
  "sizeofimage" : "0x470000",
  "timestamp" : "0xd0713de6",
  "il_offset" : "0x0002a"
 }

],
"unmanaged_frames" : [
{
"is_managed" : "false",
"native_address" : "0x172d45c4c",
"native_offset" : "0x00000"
}
,
{
"is_managed" : "false",
"native_address" : "0x172e7c788",
"native_offset" : "0x00000"
}
,
{
"is_managed" : "false",
"native_address" : "0x172e7cae4",
"native_offset" : "0x00000"
}
,
{
"is_managed" : "false",
"native_address" : "0x172e7d0d4",
"native_offset" : "0x00000"
}
,
{
"is_managed" : "false",
"native_address" : "0x172d87a20",
"native_offset" : "0x00000"
}
,
{
"is_managed" : "false",
"native_address" : "0x172d49d58",
"native_offset" : "0x00000"
}
,
{
"is_managed" : "false",
"native_address" : "0x172cd2620",
"native_offset" : "0x00000"
}
,
{
"is_managed" : "false",
"native_address" : "0x1c48bf4a4",
"native_offset" : "0x00000"
}
,
{
"is_managed" : "false",
"native_address" : "0x1009f98f0",
"native_offset" : "0x00000"
}
,
{
"is_managed" : "false",
"native_address" : "0x1009f98f0",
"native_offset" : "0x00000"
}
,
{
"is_managed" : "false",
"native_address" : "0x1009dcfd0",
"native_offset" : "0x00000"
}
,
{
"is_managed" : "false",
"native_address" : "0x1009dd69c",
"native_offset" : "0x00000"
}
,
{
"is_managed" : "false",
"native_address" : "0x1008486a4",
"native_offset" : "0x00000"
}
,
{
"is_managed" : "false",
"native_address" : "0x1008481c8",
"native_offset" : "0x00000"
}
,
{
"is_managed" : "false",
"native_address" : "0x100849224",
"native_offset" : "0x00000"
}
,
{
"is_managed" : "false",
"native_address" : "0x100b5ca58",
"native_offset" : "0x00000"
}
,
{
"is_managed" : "false",
"native_address" : "0x100b59d90",
"native_offset" : "0x00000"
}
,
{
"is_managed" : "false",
"native_address" : "0x101aec00c",
"native_offset" : "0x00000"
}
,
{
"is_managed" : "false",
"native_address" : "0x101af2a44",
"native_offset" : "0x00000"
}
,
{
"is_managed" : "false",
"native_address" : "0x101af3240",
"native_offset" : "0x00000"
}
,
{
"is_managed" : "false",
"native_address" : "0x101d6593c",
"native_offset" : "0x00000"
}
,
{
"is_managed" : "false",
"native_address" : "0x1018653dc",
"native_offset" : "0x00000"
}
,
{
"is_managed" : "false",
"native_address" : "0x100623b28",
"native_offset" : "0x00000"
}
,
{
"is_managed" : "true",
"guid" : "10F522B7-3746-4037-B248-E9A3C3BD7C67",
"token" : "0x00000",
"native_offset" : "0x0",
"filename" : "UnityEditor.CoreModule.dll",
"sizeofimage" : "0x81a000",
"timestamp" : "0x97e985a9",
"il_offset" : "0x00000"
}
,
{
"is_managed" : "true",
"guid" : "10F522B7-3746-4037-B248-E9A3C3BD7C67",
"token" : "0x6007ed4",
"native_offset" : "0x0",
"filename" : "UnityEditor.CoreModule.dll",
"sizeofimage" : "0x81a000",
"timestamp" : "0x97e985a9",
"il_offset" : "0x00000"
}
,
{
"is_managed" : "true",
"guid" : "10F522B7-3746-4037-B248-E9A3C3BD7C67",
"token" : "0x6007f3b",
"native_offset" : "0x0",
"filename" : "UnityEditor.CoreModule.dll",
"sizeofimage" : "0x81a000",
"timestamp" : "0x97e985a9",
"il_offset" : "0x00000"
}
,
{
"is_managed" : "true",
"guid" : "10F522B7-3746-4037-B248-E9A3C3BD7C67",
"token" : "0x6007dcf",
"native_offset" : "0x0",
"filename" : "UnityEditor.CoreModule.dll",
"sizeofimage" : "0x81a000",
"timestamp" : "0x97e985a9",
"il_offset" : "0x00000"
}
,
{
"is_managed" : "true",
"guid" : "10F522B7-3746-4037-B248-E9A3C3BD7C67",
"token" : "0x6007db9",
"native_offset" : "0x0",
"filename" : "UnityEditor.CoreModule.dll",
"sizeofimage" : "0x81a000",
"timestamp" : "0x97e985a9",
"il_offset" : "0x00000"
}
,
{
"is_managed" : "true",
"guid" : "10F522B7-3746-4037-B248-E9A3C3BD7C67",
"token" : "0x6001f4a",
"native_offset" : "0x0",
"filename" : "UnityEditor.CoreModule.dll",
"sizeofimage" : "0x81a000",
"timestamp" : "0x97e985a9",
"il_offset" : "0x00000"
}
,
{
"is_managed" : "true",
"guid" : "612A2C65-AAF8-43D6-98F8-D38B2AD7654A",
"token" : "0x00000",
"native_offset" : "0x0",
"filename" : "mscorlib.dll",
"sizeofimage" : "0x470000",
"timestamp" : "0xd0713de6",
"il_offset" : "0x00000"
}
,
{
"is_managed" : "false",
"native_address" : "0x172cd58e0",
"native_offset" : "0x00000"
}
,
{
"is_managed" : "false",
"native_address" : "0x172e5b6a8",
"native_offset" : "0x00000"
}
,
{
"is_managed" : "false",
"native_address" : "0x172e5b5c8",
"native_offset" : "0x00000"
}
,
{
"is_managed" : "false",
"native_address" : "0x100f00a44",
"native_offset" : "0x00000"
}
,
{
"is_managed" : "false",
"native_address" : "0x100ede87c",
"native_offset" : "0x00000"
}
,
{
"is_managed" : "false",
"native_address" : "0x10100b578",
"native_offset" : "0x00000"
}
,
{
"is_managed" : "false",
"native_address" : "0x10196eeb8",
"native_offset" : "0x00000"
}
,
{
"is_managed" : "false",
"native_address" : "0x102b5178c",
"native_offset" : "0x00000"
}
,
{
"is_managed" : "false",
"native_address" : "0x10288d738",
"native_offset" : "0x00000"
}
,
{
"is_managed" : "false",
"native_address" : "0x10288da8c",
"native_offset" : "0x00000"
}
,
{
"is_managed" : "false",
"native_address" : "0x10288d874",
"native_offset" : "0x00000"
}
,
{
"is_managed" : "false",
"native_address" : "0x102b51668",
"native_offset" : "0x00000"
}
,
{
"is_managed" : "false",
"native_address" : "0x102b4bfc4",
"native_offset" : "0x00000"
}
,
{
"is_managed" : "false",
"native_address" : "0x102b4c118",
"native_offset" : "0x00000"
}
,
{
"is_managed" : "false",
"native_address" : "0x1c7c4a1fc",
"native_offset" : "0x00000"
}
,
{
"is_managed" : "false",
"native_address" : "0x1c7648e6c",
"native_offset" : "0x00000"
}
,
{
"is_managed" : "false",
"native_address" : "0x102b3cfd4",
"native_offset" : "0x00000"
}
,
{
"is_managed" : "false",
"native_address" : "0x1c79030f4",
"native_offset" : "0x00000"
}
,
{
"is_managed" : "false",
"native_address" : "0x1c74cb008",
"native_offset" : "0x00000"
}
,
{
"is_managed" : "false",
"native_address" : "0x1c749c6fc",
"native_offset" : "0x00000"
}
,
{
"is_managed" : "false",
"native_address" : "0x102b3d6e8",
"native_offset" : "0x00000"
}
,
{
"is_managed" : "false",
"native_address" : "0x102b3da20",
"native_offset" : "0x00000"
}
,
{
"is_managed" : "false",
"native_address" : "0x105f9d08c",
"native_offset" : "0x00000"
}

]
}
]
}